{
	"$schema": "https://json-schema.org/draft/2020-12/schema",
	"type": "object",
	"properties": {
		"id": {
			"type": "integer",
			"description": "Primary unique number that represents this effect. For additional IDs that represent the same effect, check `variantIds`"
		},
		"name": {
			"type": "string",
			"description": "Primary identifier of the effect"
		},
		"icon": {
			"type": "string",
			"description": "URL of the image file as provided by ArenaNet",
			"format": "uri"
		},
		"stacking": {
			"type": ["string", "boolean"],
			"description": "Whether the effect stacks in duration, intensity, discrete charges, simply refreshes duration, or does not stack at all",
			"enum": ["Duration", "Intensity", "Refresh", false]
		},
		"maxStacks": {
			"type": ["integer", "null"],
			"description": "How many total stacks can be applied at once"
		},
		"maxDuration": {
			"type": ["integer", "null"],
			"description": "The maximum duration in seconds of the effect"
		},
		"description": {
			"type": "string",
			"description": "Additional text that provides an explanation for the effect"
		},
		"type": {
			"type": "string",
			"description": "Specific categorization of the effect, which indicates how it is applied and what other properties that it may have",
			"enum": [
				"Boon",
				"Condition",
				"Common",
				"Trait",
				"Item",
				"Skill",
				"Environment"
			]
		},
		"variantIds": {
			"type": "array",
			"description": "Additional unique IDs for effects that are essentially duplicates of the main one",
			"items": {
				"type": "integer"
			}
		}
	},
	"required": ["id", "name", "icon", "stacking"],
	"allOf": [
		{
			"if": {
				"properties": { "type": { "const": "Trait" } }
			},
			"then": {
				"properties": {
					"trait": {
						"type": "integer",
						"description": "ID of the trait that applies this effect"
					},
					"specialization": {
						"type": "integer",
						"description": "ID of the specialization that contains the related trait"
					}
				},
				"required": ["trait", "specialization"]
			}
		},
		{
			"if": {
				"properties": { "type": { "const": "Skill" } }
			},
			"then": {
				"properties": {
					"skill": {
						"type": "integer",
						"description": "ID of the skill that applies this effect"
					},
					"professions": {
						"type": "array",
						"description": "Which professions can use the related skill"
					},
					"specialization": {
						"type": "integer",
						"description": "ID of the specialization that is required to use the related skill"
					},
					"slot": {
						"type": "string",
						"description": "Where the related skill fits into"
					},
					"weapon_type": {
						"type": "string",
						"description": "Which weapon the skill is from"
					}
				},
				"required": ["skill"]
			}
		}
	]
}
